sendtomail
