Metadata-Version: 2.1
Name: sendtomail
Version: 0.3.4
Summary: Free SMTP email sender using virtual email address.
Home-page: https://github.com/mishakorzik/sendtomail
Author: MishaKorzhik_He1Zen
Author-email: developer.mishakorzhik@gmail.com
License: Apache 2.0
Project-URL: Bug Tracker, https://github.com/mishakorzik/sendtomail/issues
Project-URL: Sponsor, https://www.buymeacoffee.com/mishakorzik
Keywords: smtp,pip,pypi,email,virtual,send,server,sender,emails,email address,imap,pop3,temp mail,tempmail,temp-mail,smtplib,virtual mail,mail
Classifier: Development Status :: 5 - Production/Stable
Classifier: License :: OSI Approved :: Apache Software License
Classifier: Natural Language :: English
Classifier: Operating System :: OS Independent
Classifier: Programming Language :: Python
Classifier: Programming Language :: Python :: 3
Classifier: Programming Language :: Python :: 3.4
Classifier: Programming Language :: Python :: 3.5
Classifier: Programming Language :: Python :: 3.6
Classifier: Programming Language :: Python :: 3.7
Classifier: Programming Language :: Python :: 3.8
Classifier: Programming Language :: Python :: 3.9
Classifier: Programming Language :: Python :: 3.10
Classifier: Programming Language :: Python :: 3.11
Classifier: Programming Language :: Python :: Implementation :: CPython
Classifier: Programming Language :: Python :: Implementation :: PyPy
Classifier: Topic :: Software Development :: Libraries
Requires-Python: >=3.4
